{
    "utilisateurs": [
        {
            "indice": 0,
            "prenom": "flavio",
            "nom": "Martins soares",
            "date_naissance": "2007-07-22",
            "mail": "soares.flavio2002@gmail.com",
            "mdp": "$2y$10$mSnokBUeBsYhNiSn78jYD.mMorfLuB.ghQzp\/eRg4QZpcNObVo9N2",
            "reseau": "Facebook",
            "referent": [
                {
                    "indice": null,
                    "nom": "c",
                    "prenom": "c",
                    "mail": "c@gmail.com",
                    "reseau": "c",
                    "date_naissance": "2001-10-10",
                    "commentaire": "a",
                    "duree": "c",
                    "engagement": "c",
                    "savoir_etre": null
                }
            ]
        },
        {
            "indice": 1,
            "prenom": "Flavio",
            "nom": "MARTINS SOARES",
            "date_naissance": "2007-07-22",
            "mail": "soares.flavio2002@gmail.com",
            "mdp": "$2y$10$zRq3bQ.UI8NQrY9Pn.03lu.3Dv2yqyVblIcntaqJ.FWlASlMDEGPW",
            "reseau": "Facebook",
            "referent": []
        },
        {
            "indice": 2,
            "prenom": "Flavio",
            "nom": "MARTINS SOARES",
            "date_naissance": "2007-07-22",
            "mail": "soares.flavio2002@gmail.com",
            "mdp": "$2y$10$OunroRXLEra7HKg1B5TMcOjIvwURnax616gV.zgQhzFKvJcvhT0MW",
            "reseau": "Facebook",
            "referent": []
        },
        {
            "indice": 3,
            "prenom": "Flavio",
            "nom": "MARTINS SOARES",
            "date_naissance": "2007-07-22",
            "mail": "soares.flavio2002@gmail.com",
            "mdp": "$2y$10$hq\/xILHJpzgjqqoJfCat\/.V6mDd5YZzq.twV3eSEY.f8CnuOefufe",
            "reseau": "Facebook",
            "referent": []
        },
        {
            "indice": 4,
            "prenom": "Flavio",
            "nom": "MARTINS SOARES",
            "date_naissance": "2007-07-22",
            "mail": "soares.flavio2002@gmail.com",
            "mdp": "$2y$10$H63Xlt9ZVEZWNXDphkX4iudHuEtsSzRMbHUmL6\/mOScigrc3tr\/7m",
            "reseau": "Facebook",
            "referent": []
        },
        {
            "indice": 5,
            "prenom": "Flavio",
            "nom": "MARTINS SOARE",
            "date_naissance": "2007-07-22",
            "mail": "bezrzr@gmil.com",
            "mdp": "$2y$10$g4iHTV\/v.qEYl6MUtWFLlu6\/\/sHJcnOpfbDqpx5t8BoY2T1bi9IjS",
            "reseau": "Facebook",
            "referent": []
        },
        {
            "indice": 6,
            "prenom": "Z",
            "nom": "B",
            "date_naissance": "2007-07-22",
            "mail": "ddzdz@gmail.com",
            "mdp": "$2y$10$87X5Zpjln74nrkm.XoUElu37TA.3oSQgt0q\/HdQA.Ij5GSV9oDCLG",
            "reseau": "Facebook",
            "referent": [
                {
                    "indice": 0,
                    "nom": "theo",
                    "prenom": "fortier",
                    "mail": "theo@gmail.com",
                    "reseau": "Facebook",
                    "date_naissance": "2007-07-22",
                    "commentaire": "",
                    "engagement": "flavio mario",
                    "duree": "apagnan ann\u00e9e",
                    "savoir_etre": [
                        "Autonome",
                        "R\u00e9fl\u00e9chi",
                        "A l'\u00e9coute",
                        "Organis\u00e9"
                    ]
                }
            ]
        },
        {
            "indice": 7,
            "prenom": "Zinedine",
            "nom": "BENZOUA",
            "date_naissance": "2007-07-22",
            "mail": "zinedinebenzoua@gmail.com",
            "mdp": "$2y$10$RLarCOLbR7XkI6\/C.DrWve9SEiIoo7Dala9kpEEWbt.VBO8DFZSqy",
            "reseau": "Facebook",
            "referent": [
                {
                    "indice": 0,
                    "nom": "Fortier",
                    "prenom": "Theo",
                    "mail": "t.fortier901@gmail.com",
                    "reseau": "Facebook",
                    "date_naissance": "2007-07-22",
                    "commentaire": "",
                    "engagement": "Flop",
                    "duree": "2ans",
                    "savoir_etre": []
                },
                {
                    "indice": 1,
                    "nom": "a",
                    "prenom": "b",
                    "mail": "t.fortier901@gmail.com",
                    "reseau": "Facebook",
                    "date_naissance": "2007-07-22",
                    "commentaire": "",
                    "engagement": "oi",
                    "duree": "8ans",
                    "savoir_etre": []
                },
                {
                    "indice": 2,
                    "nom": "a",
                    "prenom": "a",
                    "mail": "t.fortier901@gmail.com",
                    "reseau": "Facebook",
                    "date_naissance": "2007-07-22",
                    "commentaire": "",
                    "engagement": "a",
                    "duree": "a",
                    "savoir_etre": []
                },
                {
                    "indice": 3,
                    "nom": "a",
                    "prenom": "a",
                    "mail": "t.fortier901@gmail.com",
                    "reseau": "Facebook",
                    "date_naissance": "2007-07-22",
                    "commentaire": "",
                    "engagement": "a",
                    "duree": "a",
                    "savoir_etre": [
                        "Autonome",
                        "Passion\u00e9",
                        "A l'\u00e9coute",
                        "Organis\u00e9"
                    ]
                },
                {
                    "indice": 4,
                    "nom": "a",
                    "prenom": "a",
                    "mail": "zinedinebenzoua@gmail.com",
                    "reseau": "Facebook",
                    "date_naissance": "2007-07-22",
                    "commentaire": "",
                    "engagement": "a",
                    "duree": "a",
                    "savoir_etre": [
                        "Passion\u00e9"
                    ]
                },
                {
                    "indice": 5,
                    "nom": "b",
                    "prenom": "b",
                    "mail": "mrglutch@gmail.com",
                    "reseau": "Facebook",
                    "date_naissance": "2007-07-22",
                    "commentaire": "",
                    "engagement": "a",
                    "duree": "a",
                    "savoir_etre": []
                }
            ]
        },
        {
            "indice": 8,
            "prenom": "a",
            "nom": "b",
            "date_naissance": "2007-07-22",
            "mail": "a@gmail.com",
            "mdp": "$2y$10$L9EGfXP8PlWNraMrqd2BMOO0R4ktOJjPRaDKseoMcND8OpP.RwrSG",
            "reseau": "Facebook",
            "referent": []
        }
    ]
}